data_convertible/__init__.py
data_convertible/main.py
data_convertible/prompts.py
data_convertible-2025.12.21173829.dist-info/METADATA
data_convertible-2025.12.21173829.dist-info/WHEEL
data_convertible-2025.12.21173829.dist-info/top_level.txt
data_convertible-2025.12.21173829.dist-info/RECORD
