Metadata-Version: 2.4
Name: data-convertible
Version: 2025.12.21173829
Summary: A new package that provides a structured and reliable way to process user input related to common developer utilities such as JSON, Base64, URL, and hash operations. It uses an LLM to interpret user r
Author-email: data-convertible <hi@eugene.plus>
License: MIT
Project-URL: Homepage, https://github.com/chigwell/data-convertible
Requires-Python: >=3.9
Requires-Dist: langchain-llm7>=0.0.0
Requires-Dist: llmatch-messages>=0.0.0
Requires-Dist: langchain-core>=0.3.0
